socketio_pg/__init__.py
socketio_pg/app.py
socketio_pg/model.py
socketio_pg/server.py
socketio_pg/websocket.py
socketio_pg-0.4.dist-info/METADATA
socketio_pg-0.4.dist-info/RECORD
socketio_pg-0.4.dist-info/WHEEL
socketio_pg-0.4.dist-info/top_level.txt
