Metadata-Version: 2.1
Name: socketio-pg
Version: 0.4
Summary: Websocket server using PostgreSQL as a message transport. Uses SocketIO, Greenlet, Flask.
Home-page: http://github.com/revmischa/socketio_pg
Author: Mischa Spiegelmock
Author-email: revmischa@cpan.org
License: ABRMS
Keywords: websocket pubsub socketio socket.io greenlet eventlet postgresql postgres psycopg2 server
Platform: UNKNOWN
